readpdfs/__init__.py
readpdfs/client.py
readpdfs-0.1.74.dist-info/LICENSE
readpdfs-0.1.74.dist-info/METADATA
readpdfs-0.1.74.dist-info/WHEEL
readpdfs-0.1.74.dist-info/top_level.txt
readpdfs-0.1.74.dist-info/RECORD
