Metadata-Version: 2.1
Name: readpdfs
Version: 0.1.74
Summary: A Python client for the ReadPDFs API
Author-email: Carbs <carbs@readpdfs.com>
Project-URL: Homepage, https://github.com/yourusername/readpdfs
Project-URL: Bug Tracker, https://github.com/yourusername/readpdfs/issues
Classifier: Programming Language :: Python :: 3
Classifier: License :: OSI Approved :: MIT License
Classifier: Operating System :: OS Independent
Requires-Python: >=3.7
License-File: LICENSE
Requires-Dist: requests >=2.25.1
